Metadata-Version: 2.1
Name: aimstool
Version: 0.1.1
Summary: A tool leveraging aimslib
Home-page: https://github.com/JonHurst/aimstool
Author: Jon Hurst
Author-email: jon.a@hursts.org.uk
License: UNKNOWN
Platform: UNKNOWN
Classifier: Development Status :: 2 - Pre-Alpha
Classifier: Environment :: Console
Classifier: Programming Language :: Python :: 3
Classifier: License :: OSI Approved :: GNU General Public License v3 or later (GPLv3+)
Classifier: Operating System :: OS Independent
Requires-Python: >=3.7
